sthira.py
sthira-0.2.0.dist-info/LICENSE
sthira-0.2.0.dist-info/WHEEL
sthira-0.2.0.dist-info/METADATA
sthira-0.2.0.dist-info/RECORD
