Metadata-Version: 2.1
Name: sthira
Version: 0.2.0
Summary: The `Constant` class is a metaclass for creating classes with constant attributes
License: MIT
Author: neelabalan
Author-email: neelabalan.n@outlook.com
Requires-Python: >=3.8,<4.0
Classifier: License :: OSI Approved :: MIT License
Classifier: Programming Language :: Python :: 3
Classifier: Programming Language :: Python :: 3.8
Classifier: Programming Language :: Python :: 3.9
Classifier: Programming Language :: Python :: 3.10
Classifier: Programming Language :: Python :: 3.11
